h5py-stubs/__init__.pyi
h5py-stubs/_hl/__init__.pyi
h5py-stubs/_hl/attrs.pyi
h5py-stubs/_hl/base.pyi
h5py-stubs/_hl/dataset.pyi
h5py-stubs/_hl/datatype.pyi
h5py-stubs/_hl/files.pyi
h5py-stubs/_hl/group.pyi
h5py-stubs/_objects.pyi
h5py-stubs/h5d.pyi
h5py-stubs/h5f.pyi
h5py-stubs/h5g.pyi
h5py-stubs/h5t.pyi
h5py_stubs-0.1.2.dist-info/WHEEL
h5py_stubs-0.1.2.dist-info/METADATA
h5py_stubs-0.1.2.dist-info/RECORD
